dashai_test_mlp_image_classifier_model/__init__.py
dashai_test_mlp_image_classifier_model/mlp_image_classifier.py
dashai_test_mlp_image_classifier_model-0.0.2.dist-info/METADATA
dashai_test_mlp_image_classifier_model-0.0.2.dist-info/WHEEL
dashai_test_mlp_image_classifier_model-0.0.2.dist-info/entry_points.txt
dashai_test_mlp_image_classifier_model-0.0.2.dist-info/licenses/LICENSE
dashai_test_mlp_image_classifier_model-0.0.2.dist-info/RECORD
