Metadata-Version: 2.3
Name: dashai_test_mlp_image_classifier_model
Version: 0.0.2
Summary: A simple MLP image classifier model for DashAI
Project-URL: Homepage, https://github.com/DashAISoftware/DashAI
Project-URL: Issues, https://github.com/DashAISoftware/DashAI/issues
Author: DashAI team
Author-email: dashaisoftware@gmail.com
License-File: LICENSE
Keywords: DashAI,Model
Requires-Python: >=3.8
Requires-Dist: torchvision==0.14.0
